silero_vad_axera/SileroAx.py
silero_vad_axera/SileroOrt.py
silero_vad_axera/__init__.py
silero_vad_axera/model.py
silero_vad_axera/utils_vad.py
silero_vad_axera/data/__init__.py
silero_vad_axera/data/silero_vad.onnx
silero_vad_axera/data/silero_vad_ax630c.axmodel
silero_vad_axera/data/silero_vad_ax650.axmodel
silero_vad_axera-0.1.1.dist-info/METADATA
silero_vad_axera-0.1.1.dist-info/WHEEL
silero_vad_axera-0.1.1.dist-info/licenses/LICENSE
silero_vad_axera-0.1.1.dist-info/RECORD
