Metadata-Version: 2.4
Name: silero-vad-axera
Version: 0.1.1
Summary: Voice Activity Detector (VAD) by Silero
Project-URL: Homepage, https://github.com/ml-inory/silero-vad.axera
Project-URL: Issues, https://github.com/ml-inory/silero-vad.axera/issues
Author-email: Axera Team <hello@axera-tech.com>
License-File: LICENSE
Classifier: Development Status :: 5 - Production/Stable
Classifier: Intended Audience :: Developers
Classifier: Intended Audience :: Science/Research
Classifier: License :: OSI Approved :: MIT License
Classifier: Operating System :: OS Independent
Classifier: Programming Language :: Python :: 3.10
Classifier: Programming Language :: Python :: 3.11
Classifier: Programming Language :: Python :: 3.12
Classifier: Programming Language :: Python :: 3.13
Classifier: Programming Language :: Python :: 3.14
Classifier: Programming Language :: Python :: 3.15
Classifier: Topic :: Scientific/Engineering
Classifier: Topic :: Scientific/Engineering :: Artificial Intelligence
Requires-Python: >=3.10
Requires-Dist: librosa==0.9.1
Requires-Dist: numpy<2.0
Requires-Dist: onnxruntime>=1.16.1
Requires-Dist: packaging
Requires-Dist: soundfile
Provides-Extra: test
Requires-Dist: pytest; extra == 'test'
Requires-Dist: soundfile; extra == 'test'
